migra/__init__.py
migra/changes.py
migra/command.py
migra/migra.py
migra/statements.py
migra/util.py
migra_maintained-1.1.0.dist-info/LICENSE
migra_maintained-1.1.0.dist-info/METADATA
migra_maintained-1.1.0.dist-info/WHEEL
migra_maintained-1.1.0.dist-info/entry_points.txt
migra_maintained-1.1.0.dist-info/RECORD
