Metadata-Version: 2.3
Name: migra-maintained
Version: 1.1.0
Summary: Like `diff` but for PostgreSQL schemas
License: Unlicense
Author: Robert Lechte
Author-email: robertlechte@gmail.com
Requires-Python: >=3.9,<4
Classifier: License :: OSI Approved
Classifier: Programming Language :: Python :: 3
Classifier: Programming Language :: Python :: 3.9
Classifier: Programming Language :: Python :: 3.10
Classifier: Programming Language :: Python :: 3.11
Classifier: Programming Language :: Python :: 3.12
Classifier: Programming Language :: Python :: 3.13
Provides-Extra: pg
Requires-Dist: greenlet (>=3.2.2,<4.0.0)
Requires-Dist: psycopg2-binary (>=2.9.7,<3) ; extra == "pg"
Requires-Dist: schema-inspect-maintained (>=1.1.2)
Requires-Dist: setuptools (>=80.8.0,<81.0.0)
Requires-Dist: six
Requires-Dist: sqlbag
Project-URL: Homepage, https://databaseci.com/docs/migra
Project-URL: Repository, https://github.com/djrobstep/migra
